kiso/__main__.py
kiso/configuration.py
kiso/constants.py
kiso/display.py
kiso/edge.py
kiso/errors.py
kiso/ip.py
kiso/log.py
kiso/objects.py
kiso/schema.py
kiso/task.py
kiso/utils.py
kiso/version.py
kiso/version.txt
kiso/apptainer/__init__.py
kiso/apptainer/apptainer.sh
kiso/apptainer/configuration.py
kiso/apptainer/installer.py
kiso/apptainer/main.yml
kiso/apptainer/schema.py
kiso/commons/init.sh
kiso/commons/main.yml
kiso/docker/__init__.py
kiso/docker/configuration.py
kiso/docker/installer.py
kiso/docker/main.yml
kiso/docker/schema.py
kiso/htcondor/__init__.py
kiso/htcondor/configuration.py
kiso/htcondor/htcondor.sh
kiso/htcondor/installer.py
kiso/htcondor/main.yml
kiso/htcondor/pegasus.sh
kiso/htcondor/schema.py
kiso/ollama/__init__.py
kiso/ollama/configuration.py
kiso/ollama/installer.py
kiso/ollama/main.yml
kiso/ollama/ollama.sh
kiso/ollama/schema.py
kiso/pegasus/__init__.py
kiso/pegasus/configuration.py
kiso/pegasus/display.py
kiso/pegasus/runner.py
kiso/pegasus/schema.py
kiso/shell/__init__.py
kiso/shell/configuration.py
kiso/shell/display.py
kiso/shell/runner.py
kiso/shell/schema.py
kiso-0.1.0a8.dist-info/licenses/LICENSE.md
kiso-0.1.0a8.dist-info/METADATA
kiso-0.1.0a8.dist-info/WHEEL
kiso-0.1.0a8.dist-info/entry_points.txt
kiso-0.1.0a8.dist-info/top_level.txt
kiso-0.1.0a8.dist-info/RECORD
