Metadata-Version: 2.4
Name: kiso
Version: 0.1.0a8
Summary: Kiso experiment manager
Author-email: Rajiv Mayani <mayani@isi.edu>
Maintainer-email: Rajiv Mayani <mayani@isi.edu>
License-Expression: Apache-2.0
Project-URL: Homepage, https://pegasus.isi.edu
Project-URL: Repository, https://github.com/pegasus-isi/kiso.git
Project-URL: Issues, https://github.com/pegasus-isi/kiso/issues
Project-URL: Changelog, https://github.com/pegasus-isi/kiso/blob/main/CHANGELOG.md
Project-URL: Documentation, https://kiso.readthedocs.io/en/latest/
Classifier: Development Status :: 3 - Alpha
Classifier: Programming Language :: Python
Classifier: Programming Language :: Python :: 3
Classifier: Programming Language :: Python :: 3.9
Classifier: Programming Language :: Python :: 3.10
Classifier: Programming Language :: Python :: 3.11
Classifier: Programming Language :: Python :: 3.12
Classifier: Programming Language :: Python :: 3.13
Classifier: Programming Language :: Python :: 3.14
Classifier: Operating System :: MacOS
Classifier: Operating System :: POSIX
Classifier: Operating System :: POSIX :: Linux
Classifier: Environment :: Console
Classifier: Intended Audience :: Science/Research
Classifier: Topic :: Scientific/Engineering
Requires-Python: >=3.9
License-File: LICENSE.md
Requires-Dist: enoslib>=10.4.0
Requires-Dist: rich-click
Requires-Dist: jsonschema<3.3
Requires-Dist: jsonschema-pyref
Requires-Dist: PyYAML
Requires-Dist: dacite
Provides-Extra: all
Requires-Dist: kiso[vagrant]; extra == "all"
Requires-Dist: kiso[chameleon]; extra == "all"
Requires-Dist: kiso[fabric]; extra == "all"
Provides-Extra: vagrant
Requires-Dist: enoslib[vagrant]; extra == "vagrant"
Provides-Extra: chameleon
Requires-Dist: enoslib[chameleon]; extra == "chameleon"
Provides-Extra: fabric
Requires-Dist: enoslib[fabric]; extra == "fabric"
Dynamic: license-file
